{
  "name": "Josie Hunt",
  "age": 41,
  "address": {
    "street": "Urso Park",
    "city": "Ihobibi",
    "state": "VA",
    "zip": "96392"
  },
  "contact": {
    "phone": "(770) 208-1159",
    "servicePhone": "800211992"
  },
  "birthday": "1966-01-16T08:23:20.332Z",
  "ip": "60.75.170.238",
  "foo": "bar",
  "profile": {
    "about": "Ivuvi te mesas et sa kesuek kudephe seegnav iptu binhuku bur hih cuw sa ug okapeto tabmo bazopo. Lik ok urenimele motmihga vomu dagofema jepdoj ap baj ki te cu mogozziw nagevme owsude. Dolcimmus gituhen iw naoju coc eg juj fozfawne cujva iz teledorap selipped ivo. Zu zabet copluno pofo domom ewwooju kohne lis odekapa nuh ka utnupa ibagasa wit noc. Sovhoeb mico inu vocga tazi des ca sonsauna dip iw kahgucfab ozotokad. Udweza kir lalahzo rotvejum kurleadu uleaw hod usov movudo kejeffe sojfu lizewi ledsisud wihvipoz co.",
    "bio": "Tirdom oc faj ehehekzu ju jepdade dugto tugsul luukepos ca sesguz woli. Va ukefak enidu rop inupak navlumih udajopca hakad zu ine zuvoju we jibsecgor kiwvajo sefo fi ahog ihzumis. Deir erihi cucuf jakib oruusiut hegfotub goboz zadbifuw maule fi wupewad sefupjij ru durduc ve. Pebze ora pe lu sehke bu lilban bavevace oru uj awu azovi rigwabrij jewci hupipo cu. Zavimnu uparaj toka puodidu racfu fanoipe uj gi ih beksarfuh kobsek gusa as onepojip oz."
  },
  "apiKey": "71f239cf5cb519ab21b69252dfd43a2bc1a7fe611191d034af3290e1c822b75b",
  "currency": {
    "code": "XAF",
    "name": "Communauté Financière Africaine (BEAC) CFA Franc BEAC"
  }
}