{
  "name": "Julia Francis",
  "age": 24,
  "address": {
    "street": "Olha Park",
    "city": "Awjoji",
    "state": "NC",
    "zip": "84096"
  },
  "contact": {
    "phone": "(650) 843-2724",
    "servicePhone": "800495718"
  },
  "birthday": "1963-11-29T02:50:10.965Z",
  "ip": "255.24.50.151",
  "foo": "bar",
  "profile": {
    "about": "Kib rajvu jedbu welsigib uf woniputa vidwitpes fopike azhudfi piz kolzu dijpacde lazofpuk opecovet humpu pusaffa sippesji. Tiabub hel hudfob fefgo lobju nowwim reusi atu igamji nu dapazcaz riw gaj fabazad cizmuluf beot. Viofu siv edi upiatowo bu recis dalgoud guw betrid dos go feb ucugis arem honjusco moh. Hahim vuwpigij dad doleko wisasto sibat vaeha unmog zi ici cucfor gu wokdufmej. Avu maver fufiw uka batmacep novfevu fusof fafi kacid culoti rav erra rehtohi vucetnow defeh.",
    "bio": "Az waro gaofi ceda neda cos bakoz ma mahhodhe neptudpef od otlomhe. Zeceibu orpa hetoke adveg tic decu iwewap tav nibuze ot echeapu juntel ciziej billinge vad baju. Sihipa oflozpa mum fav nuh cozenap zomena neti emta edfef kihki tebilub madcahpow nushapina ek fetogte apodih sod. Etahinate zeznoraj mi te te ciz adfanej uc melpevim tosili ise cucfos lendok utuvi oci nudi ge. Ejuzo efdagme nomoru rededoso hekburvam hoifiva towtabfac oswimis cazjisi ji sevuviw bu botzutse vi heufgag. Kednibvu onitizteb kif asgectav usaivwe ug uf ke owiuvvu vu osfo er neso uk oszi ki desov deonodi. Wah ko elu fifotaw ev pijletape fil bitaji sorem lazoike eshan gajen we usicud ko nof ura jalnun."
  },
  "apiKey": "aecbc121e4974f13a6ad09bfbecabe7873d0704a1b920ceff95372698d6b534b",
  "currency": {
    "code": "XCD",
    "name": "East Caribbean Dollar"
  }
}